rixa/LICENSE
rixa/MANIFEST.in
rixa/__init__.py
rixa/manage.py
rixa/pyproject.toml
rixa/setup.cfg
rixa/setup.py
rixa/RIXA.egg-info/PKG-INFO
rixa/RIXA.egg-info/SOURCES.txt
rixa/RIXA.egg-info/dependency_links.txt
rixa/RIXA.egg-info/entry_points.txt
rixa/RIXA.egg-info/requires.txt
rixa/RIXA.egg-info/top_level.txt
rixa/RIXAWebserver/__init__.py
rixa/RIXAWebserver/asgi.py
rixa/RIXAWebserver/settings.py
rixa/RIXAWebserver/urls.py
rixa/RIXAWebserver/wsgi.py
rixa/account_managment/__init__.py
rixa/account_managment/admin.py
rixa/account_managment/apps.py
rixa/account_managment/models.py
rixa/account_managment/urls.py
rixa/account_managment/views.py
rixa/account_managment/visit_statistics.py
rixa/account_managment/__pycache__/__init__.cpython-311.pyc
rixa/account_managment/__pycache__/__init__.cpython-39.pyc
rixa/account_managment/__pycache__/admin.cpython-311.pyc
rixa/account_managment/__pycache__/admin.cpython-39.pyc
rixa/account_managment/__pycache__/apps.cpython-311.pyc
rixa/account_managment/__pycache__/apps.cpython-39.pyc
rixa/account_managment/__pycache__/models.cpython-311.pyc
rixa/account_managment/__pycache__/models.cpython-39.pyc
rixa/account_managment/__pycache__/urls.cpython-311.pyc
rixa/account_managment/__pycache__/urls.cpython-39.pyc
rixa/account_managment/__pycache__/views.cpython-311.pyc
rixa/account_managment/__pycache__/views.cpython-39.pyc
rixa/account_managment/migrations/0001_initial.py
rixa/account_managment/migrations/0002_dashboardpermissions_delete_gamepermissions.py
rixa/account_managment/migrations/__init__.py
rixa/account_managment/migrations/__pycache__/0001_initial.cpython-311.pyc
rixa/account_managment/migrations/__pycache__/0001_initial.cpython-39.pyc
rixa/account_managment/migrations/__pycache__/0002_dashboardpermissions_delete_gamepermissions.cpython-311.pyc
rixa/account_managment/migrations/__pycache__/0002_dashboardpermissions_delete_gamepermissions.cpython-39.pyc
rixa/account_managment/migrations/__pycache__/__init__.cpython-311.pyc
rixa/account_managment/migrations/__pycache__/__init__.cpython-39.pyc
rixa/account_managment/templates/base_account.html
rixa/account_managment/templates/home_account.html
RIXA-0.1.0.dev2.dist-info/LICENSE
RIXA-0.1.0.dev2.dist-info/METADATA
RIXA-0.1.0.dev2.dist-info/WHEEL
RIXA-0.1.0.dev2.dist-info/entry_points.txt
RIXA-0.1.0.dev2.dist-info/top_level.txt
RIXA-0.1.0.dev2.dist-info/RECORD
