Metadata-Version: 2.1
Name: RIXA
Version: 0.1.0.dev2
Summary: Plugin system for distributed computing inside a webserver
Author-email: Finn Schwall <finn.schwall@isob.fraunhofer.de>
Project-URL: Homepage, https://gitlab.cc-asp.fraunhofer.de/xai-hiwi/rixa/rixawebserver
Classifier: Programming Language :: Python :: 3
Classifier: Framework :: Django
Classifier: License :: OSI Approved :: Apache Software License
Classifier: Operating System :: OS Independent
License-File: LICENSE
Requires-Dist: aiohttp ==3.8.4
Requires-Dist: asgiref ==3.6.0
Requires-Dist: channels ==4.0.0
Requires-Dist: Django ==4.1.5
Requires-Dist: user-agents ==2.2.0
Requires-Dist: django-bootstrap-v5 ~=1.0.11
Requires-Dist: django-rosetta ==0.9.8
Requires-Dist: plotly ~=5.14.1
Requires-Dist: daphne ==4.0.0
Requires-Dist: jsonfield
Requires-Dist: click ~=8.1.3
Requires-Dist: Pyro5 ==5.14
Requires-Dist: python-decouple ==3.8
Requires-Dist: psutil
Requires-Dist: numpy
Requires-Dist: pandas
Requires-Dist: openai
Provides-Extra: dev
Requires-Dist: openai ; extra == 'dev'
Requires-Dist: ipython ; extra == 'dev'
Requires-Dist: matplotlib ; extra == 'dev'
Requires-Dist: sympy ; extra == 'dev'
Provides-Extra: doc
Requires-Dist: python3-sphinx ; extra == 'doc'
Requires-Dist: sphinxawesome-theme ; extra == 'doc'
Requires-Dist: sphinxcontrib-mermaid ; extra == 'doc'
Requires-Dist: myst-parser ; extra == 'doc'
Provides-Extra: standard
Requires-Dist: openai ; extra == 'standard'
Requires-Dist: numpy ; extra == 'standard'
Requires-Dist: sympy ; extra == 'standard'
